{
    "links": [
        {
            "source": "vpc-092484a9211cc29aa",
            "target": "subnet-0c0df7b282c183fed"
        },
        {
            "source": "vpc-092484a9211cc29aa",
            "target": "subnet-0f6a073bf765b06da"
        },
        {
            "source": "elb_vpc-0e977ed5956ddba32",
            "target": "i-059b7b3080c78cf5b"
        },
        {
            "source": "elb_vpc-0e977ed5956ddba32",
            "target": "i-02afc85c59b7ccaf1"
        },
        {
            "source": "vpc-0e977ed5956ddba32",
            "target": "subnet-02604c9cc77b8e035"
        },
        {
            "source": "vpc-0e977ed5956ddba32",
            "target": "subnet-02a536a8828feafde"
        },
        {
            "source": "vpc-0e977ed5956ddba32",
            "target": "subnet-030c326699e93a95e"
        },
        {
            "source": "vpc-0e977ed5956ddba32",
            "target": "subnet-0adc228183cf21a0f"
        },
        {
            "source": "vpc-0e977ed5956ddba32",
            "target": "subnet-0cf9f542ef15e1e97"
        },
        {
            "source": "vpc-0e977ed5956ddba32",
            "target": "subnet-02a344fb69bb15a2f"
        },
        {
            "source": "vpc-f6f14a9d",
            "target": "subnet-f463058f"
        },
        {
            "source": "vpc-f6f14a9d",
            "target": "subnet-553b2219"
        },
        {
            "source": "vpc-f6f14a9d",
            "target": "subnet-a7c673cc"
        },
        {
            "source": "vpc-f6f14a9d",
            "target": "subnet-9e6388c1"
        },
        {
            "source": "vpc-01f221f2199ea6268",
            "target": "subnet-0764e250352d73837"
        },
        {
            "source": "vpc-01f221f2199ea6268",
            "target": "subnet-033d2d884e39d058e"
        },
        {
            "source": "vpc-01f221f2199ea6268",
            "target": "subnet-06a1abec51ec97b09"
        },
        {
            "source": "vpc-01f221f2199ea6268",
            "target": "subnet-080bbfa0b95488100"
        }
    ],
    "root": {
        "name": "root",
        "href": "icons/aws_root.png",
        "children": [
            {
                "id": "vpc-092484a9211cc29aa",
                "state": "available",
                "cidr_block": "10.0.0.0/16",
                "name": "vpc_0",
                "size": 5,
                "href": "icons/aws_igw.png",
                "children": [
                    {
                        "name": "null",
                        "children": [],
                        "size": 1
                    },
                    {
                        "id": "subnet-0c0df7b282c183fed",
                        "az": "ap-northeast-2a",
                        "cidr_block": "10.0.0.0/24",
                        "state": "available",
                        "name": "subnet_00",
                        "size": 4,
                        "href": "icons/aws_route_table.png",
                        "children": [
                            {
                                "name": "null",
                                "children": [],
                                "size": 1
                            },
                            {
                                "id": "i-0e7109307b35571a6",
                                "type": "t2.micro",
                                "launch_time": "2021-04-05 07:39:41+00:00",
                                "state": {
                                    "Code": 80,
                                    "Name": "stopped"
                                },
                                "public_ip_address": null,
                                "public_dns_name": "",
                                "private_ip_address": "10.0.0.34",
                                "private_dns_name": "ip-10-0-0-34.ap-northeast-2.compute.internal",
                                "ami_id": "ami-07464b2b9929898f8",
                                "Security_groups": [
                                    {
                                        "GroupName": "launch-wizard-4",
                                        "GroupId": "sg-00c859ee1960caae3",
                                        "Inbound": [
                                            {
                                                "FromPort": 22,
                                                "IpProtocol": "tcp",
                                                "IpRanges": [
                                                    {
                                                        "CidrIp": "0.0.0.0/0"
                                                    }
                                                ],
                                                "Ipv6Ranges": [],
                                                "PrefixListIds": [],
                                                "ToPort": 22,
                                                "UserIdGroupPairs": []
                                            }
                                        ],
                                        "Outbound": [
                                            {
                                                "IpProtocol": "-1",
                                                "IpRanges": [
                                                    {
                                                        "CidrIp": "0.0.0.0/0"
                                                    }
                                                ],
                                                "Ipv6Ranges": [],
                                                "PrefixListIds": [],
                                                "UserIdGroupPairs": []
                                            }
                                        ]
                                    }
                                ],
                                "root_volume": {
                                    "id": "vol-034ee4339bc407148",
                                    "name": "/dev/xvda",
                                    "state": "attached",
                                    "attach_time": "2021-04-02 02:22:26+00:00",
                                    "size": 8,
                                    "type": "gp2",
                                    "throughput": null
                                },
                                "name": "inst_000",
                                "size": 3,
                                "href": "icons/aws_ec2.png",
                                "children": [
                                    {
                                        "name": "null",
                                        "children": [],
                                        "size": 1
                                    }
                                ]
                            }
                        ],
                        "Natgws": [],
                        "RouteTable": []
                    },
                    {
                        "id": "subnet-0f6a073bf765b06da",
                        "az": "ap-northeast-2b",
                        "cidr_block": "10.0.1.0/24",
                        "state": "available",
                        "name": "subnet_01",
                        "size": 4,
                        "href": "icons/aws_route_table.png",
                        "children": [
                            {
                                "name": "null",
                                "children": [],
                                "size": 1
                            }
                        ],
                        "Natgws": [],
                        "RouteTable": []
                    }
                ],
                "Igws": []
            },
            {
                "id": "vpc-0e977ed5956ddba32",
                "state": "available",
                "cidr_block": "172.16.0.0/24",
                "name": "vpc_1",
                "size": 5,
                "href": "icons/aws_igw.png",
                "children": [
                    {
                        "name": "null",
                        "children": [],
                        "size": 1
                    },
                    {
                        "id": "elb_vpc-0e977ed5956ddba32",
                        "name": "dict-LB",
                        "dns_name": "dict-LB-1719271536.ap-northeast-2.elb.amazonaws.com",
                        "policies": {
                            "AppCookieStickinessPolicies": [],
                            "LBCookieStickinessPolicies": [],
                            "OtherPolicies": []
                        },
                        "azs": [
                            "ap-northeast-2c",
                            "ap-northeast-2a"
                        ],
                        "subnet_ids": [
                            "subnet-02604c9cc77b8e035",
                            "subnet-0adc228183cf21a0f"
                        ],
                        "vpc_id": "vpc-0e977ed5956ddba32",
                        "sg": [
                            "sg-0008211f3caa07b14"
                        ],
                        "children": [
                            {
                                "name": "null",
                                "children": [],
                                "size": 1
                            }
                        ]
                    },
                    {
                        "id": "subnet-02604c9cc77b8e035",
                        "az": "ap-northeast-2c",
                        "cidr_block": "172.16.0.32/27",
                        "state": "available",
                        "name": "subnet_10",
                        "size": 4,
                        "href": "icons/aws_route_table.png",
                        "children": [
                            {
                                "name": "null",
                                "children": [],
                                "size": 1
                            }
                        ],
                        "Natgws": [],
                        "RouteTable": [
                            {
                                "DestinationCidrBlock": "172.16.0.0/24",
                                "GatewayId": "local",
                                "Origin": "CreateRouteTable",
                                "State": "active"
                            },
                            {
                                "DestinationCidrBlock": "0.0.0.0/0",
                                "GatewayId": "igw-0bd608b742e675096",
                                "Origin": "CreateRoute",
                                "State": "active"
                            }
                        ]
                    },
                    {
                        "id": "subnet-02a536a8828feafde",
                        "az": "ap-northeast-2a",
                        "cidr_block": "172.16.0.128/27",
                        "state": "available",
                        "name": "subnet_11",
                        "size": 4,
                        "href": "icons/aws_route_table.png",
                        "children": [
                            {
                                "name": "null",
                                "children": [],
                                "size": 1
                            },
                            {
                                "id": "dict-db-instance",
                                "name": "dict_db",
                                "engine": "mysql",
                                "endpoint": {
                                    "Address": "dict-db-instance.cg3qmfpgandp.ap-northeast-2.rds.amazonaws.com",
                                    "Port": 3306,
                                    "HostedZoneId": "ZLA2NUCOLGUUR"
                                },
                                "create_time": "2021-05-08 13:46:27.744000+00:00",
                                "sg": [],
                                "az": "ap-northeast-2c",
                                "vpc_id": "vpc-0e977ed5956ddba32",
                                "children": [
                                    {
                                        "name": "null",
                                        "children": [],
                                        "size": 1
                                    }
                                ]
                            }
                        ],
                        "Natgws": [],
                        "RouteTable": [
                            {
                                "DestinationCidrBlock": "172.16.0.0/24",
                                "GatewayId": "local",
                                "Origin": "CreateRouteTable",
                                "State": "active"
                            },
                            {
                                "DestinationCidrBlock": "0.0.0.0/0",
                                "InstanceId": "i-076366dc565bf2111",
                                "InstanceOwnerId": "888445523521",
                                "NetworkInterfaceId": "eni-0dc02057dd1f5acaf",
                                "Origin": "CreateRoute",
                                "State": "active"
                            }
                        ]
                    },
                    {
                        "id": "subnet-030c326699e93a95e",
                        "az": "ap-northeast-2a",
                        "cidr_block": "172.16.0.64/27",
                        "state": "available",
                        "name": "subnet_12",
                        "size": 4,
                        "href": "icons/aws_route_table.png",
                        "children": [
                            {
                                "name": "null",
                                "children": [],
                                "size": 1
                            },
                            {
                                "id": "i-02afc85c59b7ccaf1",
                                "type": "t2.micro",
                                "launch_time": "2021-05-07 16:55:13+00:00",
                                "state": {
                                    "Code": 16,
                                    "Name": "running"
                                },
                                "public_ip_address": null,
                                "public_dns_name": "",
                                "private_ip_address": "172.16.0.93",
                                "private_dns_name": "ip-172-16-0-93.ap-northeast-2.compute.internal",
                                "ami_id": "ami-0f2c95e9fe3f8f80e",
                                "Security_groups": [
                                    {
                                        "GroupName": "dict-web-sg",
                                        "GroupId": "sg-01611ff0e084ac4b4",
                                        "Inbound": [
                                            {
                                                "FromPort": 80,
                                                "IpProtocol": "tcp",
                                                "IpRanges": [
                                                    {
                                                        "CidrIp": "0.0.0.0/0"
                                                    }
                                                ],
                                                "Ipv6Ranges": [],
                                                "PrefixListIds": [],
                                                "ToPort": 80,
                                                "UserIdGroupPairs": []
                                            },
                                            {
                                                "FromPort": 22,
                                                "IpProtocol": "tcp",
                                                "IpRanges": [
                                                    {
                                                        "CidrIp": "172.16.0.19/32"
                                                    }
                                                ],
                                                "Ipv6Ranges": [],
                                                "PrefixListIds": [],
                                                "ToPort": 22,
                                                "UserIdGroupPairs": []
                                            },
                                            {
                                                "FromPort": 443,
                                                "IpProtocol": "tcp",
                                                "IpRanges": [
                                                    {
                                                        "CidrIp": "0.0.0.0/0"
                                                    }
                                                ],
                                                "Ipv6Ranges": [],
                                                "PrefixListIds": [],
                                                "ToPort": 443,
                                                "UserIdGroupPairs": []
                                            },
                                            {
                                                "FromPort": -1,
                                                "IpProtocol": "icmp",
                                                "IpRanges": [
                                                    {
                                                        "CidrIp": "0.0.0.0/0"
                                                    }
                                                ],
                                                "Ipv6Ranges": [],
                                                "PrefixListIds": [],
                                                "ToPort": -1,
                                                "UserIdGroupPairs": []
                                            }
                                        ],
                                        "Outbound": [
                                            {
                                                "IpProtocol": "-1",
                                                "IpRanges": [
                                                    {
                                                        "CidrIp": "0.0.0.0/0"
                                                    }
                                                ],
                                                "Ipv6Ranges": [],
                                                "PrefixListIds": [],
                                                "UserIdGroupPairs": []
                                            }
                                        ]
                                    }
                                ],
                                "root_volume": {
                                    "id": "vol-0da966253b8f9b30d",
                                    "name": "/dev/xvda",
                                    "state": "attached",
                                    "attach_time": "2021-05-07 16:55:14+00:00",
                                    "size": 8,
                                    "type": "gp2",
                                    "throughput": null
                                },
                                "name": "inst_120",
                                "size": 3,
                                "href": "icons/aws_ec2.png",
                                "children": [
                                    {
                                        "name": "null",
                                        "children": [],
                                        "size": 1
                                    }
                                ]
                            }
                        ],
                        "Natgws": [],
                        "RouteTable": [
                            {
                                "DestinationCidrBlock": "172.16.0.0/24",
                                "GatewayId": "local",
                                "Origin": "CreateRouteTable",
                                "State": "active"
                            },
                            {
                                "DestinationCidrBlock": "0.0.0.0/0",
                                "InstanceId": "i-076366dc565bf2111",
                                "InstanceOwnerId": "888445523521",
                                "NetworkInterfaceId": "eni-0dc02057dd1f5acaf",
                                "Origin": "CreateRoute",
                                "State": "active"
                            }
                        ]
                    },
                    {
                        "id": "subnet-0adc228183cf21a0f",
                        "az": "ap-northeast-2a",
                        "cidr_block": "172.16.0.0/27",
                        "state": "available",
                        "name": "subnet_13",
                        "size": 4,
                        "href": "icons/aws_route_table.png",
                        "children": [
                            {
                                "name": "null",
                                "children": [],
                                "size": 1
                            },
                            {
                                "id": "i-076366dc565bf2111",
                                "type": "t2.micro",
                                "launch_time": "2021-05-07 15:34:44+00:00",
                                "state": {
                                    "Code": 16,
                                    "Name": "running"
                                },
                                "public_ip_address": "15.165.190.206",
                                "public_dns_name": "",
                                "private_ip_address": "172.16.0.19",
                                "private_dns_name": "ip-172-16-0-19.ap-northeast-2.compute.internal",
                                "ami_id": "ami-00550ccc38e992b78",
                                "Security_groups": [
                                    {
                                        "GroupName": "dict-nat-sg",
                                        "GroupId": "sg-026a16bb9570fdcaa",
                                        "Inbound": [
                                            {
                                                "IpProtocol": "-1",
                                                "IpRanges": [
                                                    {
                                                        "CidrIp": "172.16.0.0/24"
                                                    }
                                                ],
                                                "Ipv6Ranges": [],
                                                "PrefixListIds": [],
                                                "UserIdGroupPairs": []
                                            },
                                            {
                                                "FromPort": 1194,
                                                "IpProtocol": "udp",
                                                "IpRanges": [
                                                    {
                                                        "CidrIp": "0.0.0.0/0"
                                                    }
                                                ],
                                                "Ipv6Ranges": [
                                                    {
                                                        "CidrIpv6": "::/0"
                                                    }
                                                ],
                                                "PrefixListIds": [],
                                                "ToPort": 1194,
                                                "UserIdGroupPairs": []
                                            },
                                            {
                                                "FromPort": 22,
                                                "IpProtocol": "tcp",
                                                "IpRanges": [
                                                    {
                                                        "CidrIp": "0.0.0.0/0"
                                                    }
                                                ],
                                                "Ipv6Ranges": [],
                                                "PrefixListIds": [],
                                                "ToPort": 22,
                                                "UserIdGroupPairs": []
                                            }
                                        ],
                                        "Outbound": [
                                            {
                                                "IpProtocol": "-1",
                                                "IpRanges": [
                                                    {
                                                        "CidrIp": "0.0.0.0/0"
                                                    }
                                                ],
                                                "Ipv6Ranges": [],
                                                "PrefixListIds": [],
                                                "UserIdGroupPairs": []
                                            }
                                        ]
                                    }
                                ],
                                "root_volume": {
                                    "id": "vol-0bdd4a02500068470",
                                    "name": "/dev/xvda",
                                    "state": "attached",
                                    "attach_time": "2021-05-07 15:34:45+00:00",
                                    "size": 8,
                                    "type": "gp2",
                                    "throughput": null
                                },
                                "name": "inst_130",
                                "size": 3,
                                "href": "icons/aws_ec2.png",
                                "children": [
                                    {
                                        "name": "null",
                                        "children": [],
                                        "size": 1
                                    }
                                ]
                            }
                        ],
                        "Natgws": [],
                        "RouteTable": [
                            {
                                "DestinationCidrBlock": "172.16.0.0/24",
                                "GatewayId": "local",
                                "Origin": "CreateRouteTable",
                                "State": "active"
                            },
                            {
                                "DestinationCidrBlock": "0.0.0.0/0",
                                "GatewayId": "igw-0bd608b742e675096",
                                "Origin": "CreateRoute",
                                "State": "active"
                            }
                        ]
                    },
                    {
                        "id": "subnet-0cf9f542ef15e1e97",
                        "az": "ap-northeast-2c",
                        "cidr_block": "172.16.0.96/27",
                        "state": "available",
                        "name": "subnet_14",
                        "size": 4,
                        "href": "icons/aws_route_table.png",
                        "children": [
                            {
                                "name": "null",
                                "children": [],
                                "size": 1
                            },
                            {
                                "id": "i-059b7b3080c78cf5b",
                                "type": "t2.micro",
                                "launch_time": "2021-05-07 16:58:14+00:00",
                                "state": {
                                    "Code": 16,
                                    "Name": "running"
                                },
                                "public_ip_address": null,
                                "public_dns_name": "",
                                "private_ip_address": "172.16.0.106",
                                "private_dns_name": "ip-172-16-0-106.ap-northeast-2.compute.internal",
                                "ami_id": "ami-0f2c95e9fe3f8f80e",
                                "Security_groups": [
                                    {
                                        "GroupName": "dict-web-sg",
                                        "GroupId": "sg-01611ff0e084ac4b4",
                                        "Inbound": [
                                            {
                                                "FromPort": 80,
                                                "IpProtocol": "tcp",
                                                "IpRanges": [
                                                    {
                                                        "CidrIp": "0.0.0.0/0"
                                                    }
                                                ],
                                                "Ipv6Ranges": [],
                                                "PrefixListIds": [],
                                                "ToPort": 80,
                                                "UserIdGroupPairs": []
                                            },
                                            {
                                                "FromPort": 22,
                                                "IpProtocol": "tcp",
                                                "IpRanges": [
                                                    {
                                                        "CidrIp": "172.16.0.19/32"
                                                    }
                                                ],
                                                "Ipv6Ranges": [],
                                                "PrefixListIds": [],
                                                "ToPort": 22,
                                                "UserIdGroupPairs": []
                                            },
                                            {
                                                "FromPort": 443,
                                                "IpProtocol": "tcp",
                                                "IpRanges": [
                                                    {
                                                        "CidrIp": "0.0.0.0/0"
                                                    }
                                                ],
                                                "Ipv6Ranges": [],
                                                "PrefixListIds": [],
                                                "ToPort": 443,
                                                "UserIdGroupPairs": []
                                            },
                                            {
                                                "FromPort": -1,
                                                "IpProtocol": "icmp",
                                                "IpRanges": [
                                                    {
                                                        "CidrIp": "0.0.0.0/0"
                                                    }
                                                ],
                                                "Ipv6Ranges": [],
                                                "PrefixListIds": [],
                                                "ToPort": -1,
                                                "UserIdGroupPairs": []
                                            }
                                        ],
                                        "Outbound": [
                                            {
                                                "IpProtocol": "-1",
                                                "IpRanges": [
                                                    {
                                                        "CidrIp": "0.0.0.0/0"
                                                    }
                                                ],
                                                "Ipv6Ranges": [],
                                                "PrefixListIds": [],
                                                "UserIdGroupPairs": []
                                            }
                                        ]
                                    }
                                ],
                                "root_volume": {
                                    "id": "vol-042ac69c4f6f4a2a4",
                                    "name": "/dev/xvda",
                                    "state": "attached",
                                    "attach_time": "2021-05-07 16:58:15+00:00",
                                    "size": 8,
                                    "type": "gp2",
                                    "throughput": null
                                },
                                "name": "inst_140",
                                "size": 3,
                                "href": "icons/aws_ec2.png",
                                "children": [
                                    {
                                        "name": "null",
                                        "children": [],
                                        "size": 1
                                    }
                                ]
                            }
                        ],
                        "Natgws": [],
                        "RouteTable": [
                            {
                                "DestinationCidrBlock": "172.16.0.0/24",
                                "GatewayId": "local",
                                "Origin": "CreateRouteTable",
                                "State": "active"
                            },
                            {
                                "DestinationCidrBlock": "0.0.0.0/0",
                                "InstanceId": "i-076366dc565bf2111",
                                "InstanceOwnerId": "888445523521",
                                "NetworkInterfaceId": "eni-0dc02057dd1f5acaf",
                                "Origin": "CreateRoute",
                                "State": "active"
                            }
                        ]
                    },
                    {
                        "id": "subnet-02a344fb69bb15a2f",
                        "az": "ap-northeast-2c",
                        "cidr_block": "172.16.0.160/27",
                        "state": "available",
                        "name": "subnet_15",
                        "size": 4,
                        "href": "icons/aws_route_table.png",
                        "children": [
                            {
                                "name": "null",
                                "children": [],
                                "size": 1
                            },
                            {
                                "id": "dict-db-instance",
                                "name": "dict_db",
                                "engine": "mysql",
                                "endpoint": {
                                    "Address": "dict-db-instance.cg3qmfpgandp.ap-northeast-2.rds.amazonaws.com",
                                    "Port": 3306,
                                    "HostedZoneId": "ZLA2NUCOLGUUR"
                                },
                                "create_time": "2021-05-08 13:46:27.744000+00:00",
                                "sg": [],
                                "az": "ap-northeast-2c",
                                "vpc_id": "vpc-0e977ed5956ddba32",
                                "children": [
                                    {
                                        "name": "null",
                                        "children": [],
                                        "size": 1
                                    }
                                ]
                            }
                        ],
                        "Natgws": [],
                        "RouteTable": [
                            {
                                "DestinationCidrBlock": "172.16.0.0/24",
                                "GatewayId": "local",
                                "Origin": "CreateRouteTable",
                                "State": "active"
                            },
                            {
                                "DestinationCidrBlock": "0.0.0.0/0",
                                "InstanceId": "i-076366dc565bf2111",
                                "InstanceOwnerId": "888445523521",
                                "NetworkInterfaceId": "eni-0dc02057dd1f5acaf",
                                "Origin": "CreateRoute",
                                "State": "active"
                            }
                        ]
                    }
                ],
                "Igws": []
            },
            {
                "id": "vpc-f6f14a9d",
                "state": "available",
                "cidr_block": "172.31.0.0/16",
                "name": "vpc_2",
                "size": 5,
                "href": "icons/aws_igw.png",
                "children": [
                    {
                        "name": "null",
                        "children": [],
                        "size": 1
                    },
                    {
                        "id": "subnet-f463058f",
                        "az": "ap-northeast-2b",
                        "cidr_block": "172.31.16.0/20",
                        "state": "available",
                        "name": "subnet_20",
                        "size": 4,
                        "href": "icons/aws_route_table.png",
                        "children": [
                            {
                                "name": "null",
                                "children": [],
                                "size": 1
                            }
                        ],
                        "Natgws": [],
                        "RouteTable": []
                    },
                    {
                        "id": "subnet-553b2219",
                        "az": "ap-northeast-2c",
                        "cidr_block": "172.31.32.0/20",
                        "state": "available",
                        "name": "subnet_21",
                        "size": 4,
                        "href": "icons/aws_route_table.png",
                        "children": [
                            {
                                "name": "null",
                                "children": [],
                                "size": 1
                            },
                            {
                                "id": "i-0004aeda4b7a0143c",
                                "type": "t2.micro",
                                "launch_time": "2021-03-16 12:16:40+00:00",
                                "state": {
                                    "Code": 80,
                                    "Name": "stopped"
                                },
                                "public_ip_address": null,
                                "public_dns_name": "",
                                "private_ip_address": "172.31.34.145",
                                "private_dns_name": "ip-172-31-34-145.ap-northeast-2.compute.internal",
                                "ami_id": "ami-0e17ad9abf7e5c818",
                                "Security_groups": [
                                    {
                                        "GroupName": "launch-wizard-3",
                                        "GroupId": "sg-088959dd6836c5e21",
                                        "Inbound": [
                                            {
                                                "FromPort": 80,
                                                "IpProtocol": "tcp",
                                                "IpRanges": [
                                                    {
                                                        "CidrIp": "0.0.0.0/0"
                                                    }
                                                ],
                                                "Ipv6Ranges": [
                                                    {
                                                        "CidrIpv6": "::/0"
                                                    }
                                                ],
                                                "PrefixListIds": [],
                                                "ToPort": 80,
                                                "UserIdGroupPairs": []
                                            },
                                            {
                                                "FromPort": 22,
                                                "IpProtocol": "tcp",
                                                "IpRanges": [
                                                    {
                                                        "CidrIp": "0.0.0.0/0"
                                                    }
                                                ],
                                                "Ipv6Ranges": [],
                                                "PrefixListIds": [],
                                                "ToPort": 22,
                                                "UserIdGroupPairs": []
                                            }
                                        ],
                                        "Outbound": [
                                            {
                                                "IpProtocol": "-1",
                                                "IpRanges": [
                                                    {
                                                        "CidrIp": "0.0.0.0/0"
                                                    }
                                                ],
                                                "Ipv6Ranges": [],
                                                "PrefixListIds": [],
                                                "UserIdGroupPairs": []
                                            }
                                        ]
                                    }
                                ],
                                "root_volume": {
                                    "id": "vol-01a3b38c51835df70",
                                    "name": "/dev/xvda",
                                    "state": "attached",
                                    "attach_time": "2021-03-16 12:16:41+00:00",
                                    "size": 8,
                                    "type": "gp2",
                                    "throughput": null
                                },
                                "name": "inst_210",
                                "size": 3,
                                "href": "icons/aws_ec2.png",
                                "children": [
                                    {
                                        "name": "null",
                                        "children": [],
                                        "size": 1
                                    }
                                ]
                            }
                        ],
                        "Natgws": [],
                        "RouteTable": []
                    },
                    {
                        "id": "subnet-a7c673cc",
                        "az": "ap-northeast-2a",
                        "cidr_block": "172.31.0.0/20",
                        "state": "available",
                        "name": "subnet_22",
                        "size": 4,
                        "href": "icons/aws_route_table.png",
                        "children": [
                            {
                                "name": "null",
                                "children": [],
                                "size": 1
                            }
                        ],
                        "Natgws": [],
                        "RouteTable": []
                    },
                    {
                        "id": "subnet-9e6388c1",
                        "az": "ap-northeast-2d",
                        "cidr_block": "172.31.48.0/20",
                        "state": "available",
                        "name": "subnet_23",
                        "size": 4,
                        "href": "icons/aws_route_table.png",
                        "children": [
                            {
                                "name": "null",
                                "children": [],
                                "size": 1
                            }
                        ],
                        "Natgws": [],
                        "RouteTable": []
                    }
                ],
                "Igws": []
            },
            {
                "id": "vpc-01f221f2199ea6268",
                "state": "available",
                "cidr_block": "10.0.0.0/16",
                "name": "vpc_3",
                "size": 5,
                "href": "icons/aws_igw.png",
                "children": [
                    {
                        "name": "null",
                        "children": [],
                        "size": 1
                    },
                    {
                        "id": "subnet-0764e250352d73837",
                        "az": "ap-northeast-2a",
                        "cidr_block": "10.0.0.0/24",
                        "state": "available",
                        "name": "subnet_30",
                        "size": 4,
                        "href": "icons/aws_route_table.png",
                        "children": [
                            {
                                "name": "null",
                                "children": [],
                                "size": 1
                            }
                        ],
                        "Natgws": [],
                        "RouteTable": [
                            {
                                "DestinationCidrBlock": "10.0.0.0/16",
                                "GatewayId": "local",
                                "Origin": "CreateRouteTable",
                                "State": "active"
                            },
                            {
                                "DestinationCidrBlock": "0.0.0.0/0",
                                "GatewayId": "igw-0ca7d7615513ba71b",
                                "Origin": "CreateRoute",
                                "State": "active"
                            }
                        ]
                    },
                    {
                        "id": "subnet-033d2d884e39d058e",
                        "az": "ap-northeast-2c",
                        "cidr_block": "10.0.3.0/24",
                        "state": "available",
                        "name": "subnet_31",
                        "size": 4,
                        "href": "icons/aws_route_table.png",
                        "children": [
                            {
                                "name": "null",
                                "children": [],
                                "size": 1
                            }
                        ],
                        "Natgws": [],
                        "RouteTable": [
                            {
                                "DestinationCidrBlock": "10.0.0.0/16",
                                "GatewayId": "local",
                                "Origin": "CreateRouteTable",
                                "State": "active"
                            },
                            {
                                "DestinationCidrBlock": "0.0.0.0/0",
                                "NetworkInterfaceId": "eni-0ed861976d61b3dac",
                                "Origin": "CreateRoute",
                                "State": "blackhole"
                            }
                        ]
                    },
                    {
                        "id": "subnet-06a1abec51ec97b09",
                        "az": "ap-northeast-2a",
                        "cidr_block": "10.0.2.0/24",
                        "state": "available",
                        "name": "subnet_32",
                        "size": 4,
                        "href": "icons/aws_route_table.png",
                        "children": [
                            {
                                "name": "null",
                                "children": [],
                                "size": 1
                            }
                        ],
                        "Natgws": [],
                        "RouteTable": [
                            {
                                "DestinationCidrBlock": "10.0.0.0/16",
                                "GatewayId": "local",
                                "Origin": "CreateRouteTable",
                                "State": "active"
                            },
                            {
                                "DestinationCidrBlock": "0.0.0.0/0",
                                "NetworkInterfaceId": "eni-0ed861976d61b3dac",
                                "Origin": "CreateRoute",
                                "State": "blackhole"
                            }
                        ]
                    },
                    {
                        "id": "subnet-080bbfa0b95488100",
                        "az": "ap-northeast-2c",
                        "cidr_block": "10.0.1.0/24",
                        "state": "available",
                        "name": "subnet_33",
                        "size": 4,
                        "href": "icons/aws_route_table.png",
                        "children": [
                            {
                                "name": "null",
                                "children": [],
                                "size": 1
                            }
                        ],
                        "Natgws": [],
                        "RouteTable": [
                            {
                                "DestinationCidrBlock": "10.0.0.0/16",
                                "GatewayId": "local",
                                "Origin": "CreateRouteTable",
                                "State": "active"
                            },
                            {
                                "DestinationCidrBlock": "0.0.0.0/0",
                                "GatewayId": "igw-0ca7d7615513ba71b",
                                "Origin": "CreateRoute",
                                "State": "active"
                            }
                        ]
                    }
                ],
                "Igws": []
            }
        ]
    }
}